boulderopalscaleupsdk/__init__.py
boulderopalscaleupsdk/agent/__init__.py
boulderopalscaleupsdk/agent/worker.py
boulderopalscaleupsdk/common/__init__.py
boulderopalscaleupsdk/common/dtypes.py
boulderopalscaleupsdk/common/typeclasses.py
boulderopalscaleupsdk/constants.py
boulderopalscaleupsdk/device/__init__.py
boulderopalscaleupsdk/device/common.py
boulderopalscaleupsdk/device/config_loader.py
boulderopalscaleupsdk/device/controller/__init__.py
boulderopalscaleupsdk/device/controller/base.py
boulderopalscaleupsdk/device/controller/qblox.py
boulderopalscaleupsdk/device/controller/quantum_machines.py
boulderopalscaleupsdk/device/controller/resolver.py
boulderopalscaleupsdk/device/defcal.py
boulderopalscaleupsdk/device/processor/__init__.py
boulderopalscaleupsdk/device/processor/common.py
boulderopalscaleupsdk/device/processor/superconducting_processor.py
boulderopalscaleupsdk/errors.py
boulderopalscaleupsdk/experiments/__init__.py
boulderopalscaleupsdk/experiments/chi01_scan.py
boulderopalscaleupsdk/experiments/classifiers.py
boulderopalscaleupsdk/experiments/common.py
boulderopalscaleupsdk/experiments/cz_leakage_calibration.py
boulderopalscaleupsdk/experiments/cz_phase_calibration.py
boulderopalscaleupsdk/experiments/cz_spectroscopy_by_bias.py
boulderopalscaleupsdk/experiments/drag_leakage_calibration.py
boulderopalscaleupsdk/experiments/fine_amplitude_calibration.py
boulderopalscaleupsdk/experiments/one_qubit_rb.py
boulderopalscaleupsdk/experiments/power_rabi.py
boulderopalscaleupsdk/experiments/power_rabi_ef.py
boulderopalscaleupsdk/experiments/process_tomography.py
boulderopalscaleupsdk/experiments/ramsey.py
boulderopalscaleupsdk/experiments/ramsey_ef.py
boulderopalscaleupsdk/experiments/readout_classifier.py
boulderopalscaleupsdk/experiments/readout_optimization.py
boulderopalscaleupsdk/experiments/resonator_spectroscopy.py
boulderopalscaleupsdk/experiments/resonator_spectroscopy_by_bias.py
boulderopalscaleupsdk/experiments/resonator_spectroscopy_by_power.py
boulder_opal_scale_up_sdk-1.0.15.dist-info/LICENSE
boulder_opal_scale_up_sdk-1.0.15.dist-info/METADATA
boulder_opal_scale_up_sdk-1.0.15.dist-info/WHEEL
boulder_opal_scale_up_sdk-1.0.15.dist-info/RECORD
