Metadata-Version: 2.3
Name: boulder-opal-scale-up-sdk
Version: 1.0.15
Summary: Q-CTRL Boulder Opal Scale Up Python SDK
License: https://q-ctrl.com/terms
Keywords: black opal,boulder opal,fire opal,nisq,open controls,q control,q ctrl,q-control,q-ctrl,qcontrol,qctrl,quantum,quantum algorithms,quantum circuits,quantum coding,quantum coding software,quantum computing,quantum control,quantum control software,quantum control theory,quantum engineering,quantum error correction,quantum firmware,quantum fundamentals,quantum sensing,qubit,qudit
Author: Q-CTRL
Author-email: support@q-ctrl.com
Maintainer: Q-CTRL
Maintainer-email: support@q-ctrl.com
Requires-Python: >=3.11,<3.13
Classifier: Development Status :: 5 - Production/Stable
Classifier: Environment :: Console
Classifier: Intended Audience :: Developers
Classifier: Intended Audience :: Education
Classifier: Intended Audience :: Science/Research
Classifier: Natural Language :: English
Classifier: Operating System :: OS Independent
Classifier: Programming Language :: Python :: 3.11
Classifier: Programming Language :: Python :: 3.12
Classifier: Topic :: Internet :: WWW/HTTP
Classifier: Topic :: Scientific/Engineering :: Physics
Classifier: Topic :: Scientific/Engineering :: Visualization
Classifier: Topic :: Software Development :: Embedded Systems
Classifier: Topic :: System :: Distributed Computing
Provides-Extra: quantum-machines
Requires-Dist: attrs (>=25.1.0,<26.0.0)
Requires-Dist: googleapis-common-protos (>=1.69.2,<1.70.0)
Requires-Dist: numpy (>=2.3.3,<3.0.0)
Requires-Dist: pydantic (>=2.10.4,<3.0.0)
Requires-Dist: pydantic-settings (>=2.7.0,<3.0.0)
Requires-Dist: python-dateutil (>=2.9.0.post0,<3.0.0)
Requires-Dist: pyyaml (>=6.0.2,<7.0.0)
Requires-Dist: qm-qua ; extra == "quantum-machines"
Project-URL: Facebook, https://www.facebook.com/qctrl
Project-URL: GitHub, https://github.com/qctrl
Project-URL: Homepage, https://q-ctrl.com
Project-URL: LinkedIn, https://www.linkedin.com/company/q-ctrl/
Project-URL: X, https://x.com/qctrlHQ
Project-URL: YouTube, https://www.youtube.com/qctrl
